uuid7gen/__init__.py
uuid7gen/uuid7.py
uuid7gen-0.1.0.dist-info/LICENSE
uuid7gen-0.1.0.dist-info/METADATA
uuid7gen-0.1.0.dist-info/WHEEL
uuid7gen-0.1.0.dist-info/top_level.txt
uuid7gen-0.1.0.dist-info/RECORD
