Metadata-Version: 2.1
Name: uuid7gen
Version: 0.1.0
Summary: UUIDv7 generation for Python <3.11
Home-page: 
Author: Chowlett2
Author-email: Conor Howlett <howlettconor@gmail.com>, Adam Lashley <lashleyaq@gmail.com>, Tyler Blume <t-blume@hotmail.com>
License: MIT
Project-URL: Homepage, https://github.com/Chowlett2/uuid7gen
Project-URL: Source, https://github.com/Chowlett2/uuid7gen
Project-URL: Bug Tracker, https://github.com/Chowlett2/uuid7gen/issues
Keywords: uuid,uuid7,identifiers,time-based,python
Classifier: Programming Language :: Python :: 3
Classifier: Programming Language :: Python :: 3.7
Classifier: Programming Language :: Python :: 3.8
Classifier: Programming Language :: Python :: 3.9
Classifier: Programming Language :: Python :: 3.10
Classifier: Programming Language :: Python :: 3.11
Classifier: License :: OSI Approved :: MIT License
Classifier: Operating System :: OS Independent
Requires-Python: >=3.7
License-File: LICENSE
